{
    "controfield": [
        {
            "code": "000",
            "value": "     nam  22      a 4500"
        },
        {
            "code": "001",
            "value": "000008574"
        },
        {
            "code": "005",
            "value": "20190701182006.0"
        },
        {
            "code": "007",
            "value": "t"
        },
        {
            "code": "008",
            "value": "                                   por"
        }
    ],
    "datafield": [
        {
            "code": "020",
            "subfield": {
                "a": "8574022845"
            }
        },
        {
            "code": "040",
            "subfield": {
                "a": "BR-BrMCT"
            }
        },
        {
            "code": "090",
            "subfield": {
                "a": "657 ",
                "b": "B873u ",
                "c": "=134.3"
            }
        },
        {
            "code": "100",
            "subfield": {
                "a": "Brookson Stephen"
            }
        },
        {
            "code": "245",
            "subfield": {
                "a": "Como entender a contabilidade ",
                "c": "Stephen Brookson ; tradução Anna Quirino ",
                "h": "Impresso"
            }
        },
        {
            "code": "250",
            "subfield": {
                "a": "[2. ed.]"
            }
        },
        {
            "code": "260",
            "subfield": {
                "a": "São Paulo ",
                "b": "Publifolha ",
                "c": "2002"
            }
        },
        {
            "code": "270",
            "subfield": {
                "d": "Brasil"
            }
        },
        {
            "code": "300",
            "subfield": {
                "a": "72 ",
                "b": "il."
            }
        },
        {
            "code": "490",
            "subfield": {
                "a": "Série Sucesso Profissional"
            }
        },
        {
            "code": "500",
            "subfield": {
                "a": "Capa: Seu guia de estratégia pessoal"
            }
        },
        {
            "code": "534",
            "subfield": {
                "a": "Título original: Understanding accounts"
            }
        },
        {
            "code": "650",
            "subfield": {
                "a": "Contabilidade gerencial"
            }
        },
        {
            "code": "990",
            "subfield": {
                "a": "Monografia"
            }
        }
    ]
}