{
    "controfield": [
        {
            "code": "000",
            "value": "     nam  22      a 4500"
        },
        {
            "code": "001",
            "value": "000008735"
        },
        {
            "code": "005",
            "value": "20180713154817.0"
        },
        {
            "code": "007",
            "value": "t"
        },
        {
            "code": "008",
            "value": "                                   por"
        }
    ],
    "datafield": [
        {
            "code": "040",
            "subfield": {
                "a": "BR-BrMCT"
            }
        },
        {
            "code": "090",
            "subfield": {
                "a": "621.39(81)(063) ",
                "b": "P147q ",
                "c": "2007"
            }
        },
        {
            "code": "111",
            "subfield": {
                "a": "Painel Telebrasil : Brasil Digital surge como realidade irreversível ",
                "c": "Costa do Sauípe, BA ",
                "d": "2007 ",
                "n": "51"
            }
        },
        {
            "code": "245",
            "subfield": {
                "a": "51º Painel Telebrasil ",
                "b": "cobertura do painel executivo : o Brasil digital ",
                "h": "Impresso"
            }
        },
        {
            "code": "260",
            "subfield": {
                "a": "[S.l.] ",
                "b": "Associação Brasileira de Telecomunicações ",
                "c": "2007"
            }
        },
        {
            "code": "270",
            "subfield": {
                "d": "Brasil"
            }
        },
        {
            "code": "300",
            "subfield": {
                "a": "1 v."
            }
        },
        {
            "code": "650",
            "subfield": {
                "a": "Telecomunicações"
            }
        },
        {
            "code": "650",
            "subfield": {
                "a": "Rede de telecomunicação"
            }
        },
        {
            "code": "650",
            "subfield": {
                "a": "Rede de computador"
            }
        },
        {
            "code": "856",
            "subfield": {
                "y": "Texto Completo (Telebrasil) - Acesso em: 13/12/2017 ",
                "u": "http://www.telebrasil.org.br/51-edicao#cobertura"
            }
        },
        {
            "code": "990",
            "subfield": {
                "a": "Monografia"
            }
        }
    ]
}