{
    "controfield": {
        "000": "     nam  22      a 4500",
        "001": "000001621",
        "005": "20190813160353.0",
        "007": "t",
        "008": "                                   por"
    },
    "datafield": {
        "040": {
            "a": "BR-BrMCT",
            "c": "BR-BrMCT"
        },
        "090": {
            "a": "930.25",
            "b": "D614co",
            "c": "2003"
        },
        "110": {
            "a": "Distrito Federal (Brasil). Tribunal de Contas"
        },
        "245": {
            "a": "Código de classificação de documentos de arquivo e da tabela de temporalidade de documentos",
            "c": "Tribunal de Contas do Distrito Federal",
            "h": "Impresso"
        },
        "260": [
            {
                "a": "Brasília",
                "b": "Seção de Documentação",
                "c": "2003"
            }
        ],
        "300": [
            {
                "a": "202"
            }
        ],
        "490": [
            {
                "a": "Coleção estudos e documentos / TCDF",
                "v": "v. 2"
            }
        ],
        "505": [
            {
                "a": "Histórico -- Código de classificação de documentos de Arquivo -- Tabelas auxiliares -- Tabela de temporalidade e destinação de documentos de arquivo relativos as atividades-meio da administração pública"
            }
        ],
        "650": [
            {
                "a": "Arquivo",
                "x": "Classificação"
            }
        ],
        "990": {
            "a": "Monografia"
        }
    }
}