{
    "controfield": {
        "000": "     nam  22      a 4500",
        "001": "000003896",
        "005": "20190813121314.0",
        "007": "t",
        "008": "                                   por"
    },
    "datafield": {
        "040": {
            "a": "BR-BrMCT"
        },
        "090": {
            "a": "929:53",
            "b": "L364ce",
            "c": "1994"
        },
        "245": {
            "a": "Cesar Lattes, 70 anos",
            "b": "a nova fisica brasileira",
            "c": "editor: Alfredo Marques",
            "h": "Impresso"
        },
        "260": [
            {
                "a": "Rio de Janeiro",
                "b": "Centro Brasileiro de Pesquisas Físicas",
                "c": "1994"
            }
        ],
        "300": [
            {
                "a": "212",
                "c": "22 cm",
                "b": "il."
            }
        ],
        "500": [
            {
                "a": "Homenagem ao Prof. Cesar Lattes ao ensejo de seus 70 anos, sob os auspícios do CNPq"
            }
        ],
        "600": [
            {
                "a": "Lattes, Cesar",
                "d": "1924-"
            }
        ],
        "650": [
            {
                "a": "Físico",
                "x": "Biografia",
                "z": "Brasil"
            },
            {
                "a": "Física",
                "x": "História",
                "z": "Brasil"
            }
        ],
        "700": [
            {
                "a": "Marques, Alfredo",
                "e": "Editor"
            }
        ],
        "710": [
            {
                "a": "Centro Brasileiro de Pesquisas Físicas",
                "c": "Brasil",
                "e": "Corporativo"
            }
        ],
        "990": {
            "a": "Monografia"
        }
    }
}