{
    "controfield": {
        "000": "     nam  22      a 4500",
        "001": "000004179",
        "005": "20190812170438.0",
        "007": "t",
        "008": "                                   por"
    },
    "datafield": {
        "020": {
            "a": "858716676X"
        },
        "040": {
            "a": "BR-BrMCT"
        },
        "090": {
            "a": "574.1(81:213.5)",
            "b": "A532",
            "c": "2005"
        },
        "245": {
            "a": "Análise das variações da biodiversidade do bioma caatinga",
            "b": "suporte a estratégias regionais de conservação",
            "c": "organizadores, Francisca soares de Araújo, Maria Jesus Nogueira Rodal, Maria Regina de Vasconcellos Barbosa",
            "h": "Impresso"
        },
        "260": [
            {
                "a": "Brasília",
                "b": "Ministério do Meio Ambiente",
                "c": "2005"
            }
        ],
        "300": [
            {
                "a": "445",
                "b": "il., color"
            }
        ],
        "490": [
            {
                "a": "Biodiversidade",
                "v": "12"
            }
        ],
        "650": [
            {
                "a": "Biodiversidade",
                "z": "Caatinga"
            },
            {
                "a": "Ecossistemas",
                "z": "Caatinga"
            },
            {
                "a": "Biosfera",
                "z": "Caatinga"
            },
            {
                "a": "Ecossistemas",
                "z": "Caatinga"
            },
            {
                "a": "Conservação da natureza",
                "z": "Caatinga"
            }
        ],
        "700": [
            {
                "a": "Araújo, Francisca Soares de",
                "e": "Organizador"
            },
            {
                "a": "Rodal, Maria Jesus Nogueira",
                "e": "Organizador"
            },
            {
                "a": "Barbosa, Maria Regina de Vasconcellos",
                "e": "Organizador"
            }
        ],
        "710": [
            {
                "a": "Brasil. Ministério do Meio Ambiente",
                "b": "Secretaria de Biodiversidade e Florestas",
                "e": "Corporativo"
            }
        ],
        "856": {
            "y": "Texto completo (MMA)",
            "u": "http://www.mma.gov.br/publicacoes/biodiversidade/category/142-serie-biodiversidade?download=903:serie-biodiversidade-biodiversidade-12",
            "z": "Acesso em: 11/12/2015"
        },
        "990": {
            "a": "Monografia"
        }
    }
}