{
    "controfield": {
        "000": "     nam  22      a 4500",
        "001": "000004911",
        "005": "20190730105006.0",
        "007": "t",
        "008": "                                   por"
    },
    "datafield": {
        "020": {
            "a": "8522412588"
        },
        "040": {
            "a": "BR-BrMCT"
        },
        "090": {
            "a": "005.51",
            "b": "M667c",
            "c": "=134.3",
            "d": "1995"
        },
        "100": {
            "a": "Mintzberg, Henry",
            "d": "1939-"
        },
        "245": {
            "a": "Criando organizações eficazes",
            "b": "estruturas em cinco configurações",
            "c": "Henry Mintzberg ; tradução: Cyro Bernardes",
            "h": "Impresso"
        },
        "246": [
            {
                "a": "Struture en fives: designing effective organizations. Português"
            }
        ],
        "260": [
            {
                "a": "São Paulo",
                "b": "Atlas",
                "c": "1995"
            }
        ],
        "300": [
            {
                "a": "304",
                "c": "24 cm"
            }
        ],
        "505": [
            {
                "a": "Fundamentos da planificação organizacional -- Delineando posições individuais e superestrutura -- Preenchendo a superestrutura -- Preenchendo a superestrutura -- Desembraçando a organização -- Adaptando o plano à situação -- O plano como uma configuração -- A estrutura simples -- A burocracia mecanizada e profissional -- A forma divisionalizada -- A adhocracia -- Além das cinco configurações"
            }
        ],
        "534": {
            "a": "Traducao de: Structure in fives : designing effective organizations"
        },
        "650": [
            {
                "a": "Desenvolvimento organizacional"
            },
            {
                "a": "Planejamento empresarial"
            },
            {
                "a": "Organização"
            }
        ],
        "990": {
            "a": "Monografia"
        }
    }
}