{
    "controfield": {
        "000": "     nam  22      a 4500",
        "001": "000005187",
        "005": "20190808142102.0",
        "007": "t",
        "008": "                                   eng"
    },
    "datafield": {
        "040": {
            "a": "BR-BrMCT"
        },
        "090": {
            "a": "321.728(81)",
            "b": "M227p",
            "c": "1997"
        },
        "100": {
            "a": "Mainwaring, Scott",
            "d": "1954-"
        },
        "245": {
            "a": "Presidentialism in Brazil",
            "b": "the impact of strong constitutional powers, weak partisan powers, and robust federalism",
            "h": "Impresso",
            "c": "Scott Mainwaring"
        },
        "260": [
            {
                "a": "Washington (Distrito de Colúmbia, Estados Unidos)",
                "b": "Latin American Program, Woodrow Wilson International Center for Scholars",
                "c": "1997"
            }
        ],
        "300": [
            {
                "a": "61"
            }
        ],
        "490": [
            {
                "a": "Working paper series / Latin American Program",
                "v": "n. 225"
            }
        ],
        "650": [
            {
                "a": "Presidente",
                "z": "Brasil"
            },
            {
                "a": "Poder executivo",
                "z": "Brasil"
            },
            {
                "a": "Federalismo",
                "z": "Brasil"
            }
        ],
        "651": [
            {
                "a": "Brasil",
                "x": "História"
            }
        ],
        "990": {
            "a": "Monografia"
        }
    }
}