{
    "controfield": [
        {
            "code": "000",
            "value": "     nam  22      a 4500"
        },
        {
            "code": "001",
            "value": "000001378"
        },
        {
            "code": "005",
            "value": "20190726151121.0"
        },
        {
            "code": "007",
            "value": "t"
        },
        {
            "code": "008",
            "value": "                                   por"
        }
    ],
    "datafield": [
        {
            "code": "040",
            "subfield": {
                "a": "BR-BrMCT ",
                "c": "BR-BrMCT"
            }
        },
        {
            "code": "090",
            "subfield": {
                "a": "331.5 ",
                "b": "R175si ",
                "c": "1998"
            }
        },
        {
            "code": "100",
            "subfield": {
                "a": "Ramos, Carlos Alberto"
            }
        },
        {
            "code": "245",
            "subfield": {
                "a": "Sistema público de emprego ",
                "b": "objetivos, eficiência e eficácia; notas sobre os países da OCDE e o Brasil ",
                "c": "Carlos Alberto Ramos, Paulo Springer de Freitas ",
                "h": "Impresso"
            }
        },
        {
            "code": "260",
            "subfield": {
                "a": "Brasília ",
                "b": "Instituto de Pesquisa Econômica Aplicada ",
                "c": "1998"
            }
        },
        {
            "code": "300",
            "subfield": {
                "a": "39 f. ",
                "b": "il."
            }
        },
        {
            "code": "490",
            "subfield": {
                "a": "Texto para discussão / IPEA ",
                "v": "568 ",
                "x": "1415-4765"
            }
        },
        {
            "code": "520",
            "subfield": {
                "a": "Apresenta os fundamentos teóricos que justificam a implementação de um Sistema Público de Emprego (SPE). Trata do arcabouço institucional que articula o pagamento dos benefícios financeiros aos trabalhadores desempregados, sua formação, reciclagem e intermediação. Conclui que os SPE têm como função reduzir o desemprego que surge da imcompatibilidade entre o perfil da oferta e a demanda de mão-de-obra. Apresenta indicadores sobre a experiência dos países da OCDE e constata a ineficiência do SPE em situações de desemprego em grande escala. Avalia o sistema de intermediação realizado no Brasil pelo SINE, seu elevado custo e baixa efetividade."
            }
        },
        {
            "code": "650",
            "subfield": {
                "a": "Emprego"
            }
        },
        {
            "code": "650",
            "subfield": {
                "a": "Setor público"
            }
        },
        {
            "code": "650",
            "subfield": {
                "a": "Desemprego"
            }
        },
        {
            "code": "650",
            "subfield": {
                "a": "Mercado de trabalho"
            }
        },
        {
            "code": "650",
            "subfield": {
                "a": "Produtividade do trabalho"
            }
        },
        {
            "code": "700",
            "subfield": {
                "a": "Freitas, Paulo Springer de ",
                "e": "Coautor"
            }
        },
        {
            "code": "710",
            "subfield": {
                "a": "Instituto de Pesquisa Econômica Aplicada ",
                "c": "Brasil ",
                "e": "Corporativo"
            }
        },
        {
            "code": "856",
            "subfield": {
                "y": "IPEA ",
                "u": "http://www.ipea.gov.br/portal/images/stories/PDFs/TDs/td_0568.pdf ",
                "z": "Acesso em: 17/10/2013"
            }
        },
        {
            "code": "990",
            "subfield": {
                "a": "Folheto"
            }
        }
    ]
}